apiModels/__init__.py
apiModels/get_bibtex_from_crossref.py
apiModels/get_bibtex_from_dblp.py
apiModels/get_bibtex_from_google_scholar.py
apiModels/meta_class.py
apiModels/utils/__init__.py
apiModels/utils/verify.py
apiModels/workflow/__init__.py
apiModels/workflow/crossref2dblp.py
apiModels/workflow/make_workflow.py
get_bibtex-2.0.1.dist-info/METADATA
get_bibtex-2.0.1.dist-info/WHEEL
get_bibtex-2.0.1.dist-info/top_level.txt
get_bibtex-2.0.1.dist-info/RECORD
