Metadata-Version: 2.4
Name: get-bibtex
Version: 2.0.1
Summary: A Python tool for fetching citations from multiple sources.
Requires-Python: >=3.10
Requires-Dist: black>=23.0
Requires-Dist: flake8>=6.0
Requires-Dist: google-search-results>=2.4.2
Requires-Dist: isort>=5.12
Requires-Dist: pytest>=7.0
Requires-Dist: pytest-cov>=4.1.0
Requires-Dist: pytest-mock>=3.12.0
Requires-Dist: requests>=2.32.3
Requires-Dist: tqdm>=4.67.1
